MANIFEST.in
README.txt
setup.cfg
setup.py
oofill/__init__.py
oofill/parser.py
oofill.egg-info/PKG-INFO
oofill.egg-info/SOURCES.txt
oofill.egg-info/dependency_links.txt
oofill.egg-info/entry_points.txt
oofill.egg-info/not-zip-safe
oofill.egg-info/top_level.txt
oofill/tests/__init__.py
oofill/tests/test1.odt
oofill/tests/test1_out.odt
oofill/tests/test2.odt
oofill/tests/test2_out.odt
oofill/tests/test_1.py