Metadata-Version: 1.0
Name: oofill
Version: 1.1.0
Summary: OpenOffice blank filler
Home-page: https://svn.plonegov.org/oofill
Author: atReal
Author-email: contact@atreal.net
License: GPL
Platform: UNKNOWN
